LICENSE.txt
MANIFEST.in
README.rst
requirements-flake8.txt
requirements-rtd.txt
requirements-testing.txt
requirements.txt
setup.py
tox.ini
pip_accel/__init__.py
pip_accel/__main__.py
pip_accel/bdist.py
pip_accel/cli.py
pip_accel/compat.py
pip_accel/config.py
pip_accel/exceptions.py
pip_accel/req.py
pip_accel/tests.py
pip_accel/utils.py
pip_accel.egg-info/PKG-INFO
pip_accel.egg-info/SOURCES.txt
pip_accel.egg-info/dependency_links.txt
pip_accel.egg-info/entry_points.txt
pip_accel.egg-info/requires.txt
pip_accel.egg-info/top_level.txt
pip_accel/caches/__init__.py
pip_accel/caches/local.py
pip_accel/caches/s3.py
pip_accel/deps/__init__.py
pip_accel/deps/debian.ini